zoo_template_common/__init__.py
zoo_template_common/common_execution_handler.py
zoo_template_common/custom_stac_io.py
zoo_template_common-0.1.5.dist-info/METADATA
zoo_template_common-0.1.5.dist-info/WHEEL
zoo_template_common-0.1.5.dist-info/RECORD
