Metadata-Version: 2.4
Name: zoo-template-common
Version: 0.1.5
Summary: Shared utilities and base service templates for ZOO CWL runners
License: Apache-2.0
Keywords: zoo-project,cwl,template,eoepca,stac,workflow
Author: Aryan Khare
Author-email: kharearyan78@gmail.com
Requires-Python: >=3.10
Classifier: Development Status :: 4 - Beta
Classifier: Intended Audience :: Developers
Classifier: License :: OSI Approved :: Apache Software License
Classifier: Programming Language :: Python :: 3
Classifier: Programming Language :: Python :: 3.10
Classifier: Programming Language :: Python :: 3.11
Classifier: Programming Language :: Python :: 3.12
Classifier: Programming Language :: Python :: 3.13
Classifier: Programming Language :: Python :: 3.14
Requires-Dist: boto3 (>=1.28.0)
Requires-Dist: botocore (>=1.31.0)
Requires-Dist: loguru (>=0.7.0)
Requires-Dist: pystac (>=1.8.0)
Requires-Dist: pyyaml (>=6.0)
Requires-Dist: zoo-runner-common (>=0.1.3)
Project-URL: Documentation, https://zoo-project.github.io/zoo-template-common/
Project-URL: Homepage, https://github.com/ZOO-Project/zoo-template-common
Project-URL: Repository, https://github.com/ZOO-Project/zoo-template-common
